django_npb-1.1.1.data/data/license/LICENSE-EN.txt
django_npb-1.1.1.data/data/license/LICENSE-FR.txt
npb/__init__.py
npb/admin.py
npb/apps.py
npb/forms.py
npb/ip.py
npb/models.py
npb/urls.py
npb/views.py
npb/locale/en/LC_MESSAGES/django.mo
npb/locale/en/LC_MESSAGES/django.po
npb/locale/fr/LC_MESSAGES/django.mo
npb/locale/fr/LC_MESSAGES/django.po
npb/management/__init__.py
npb/management/commands/__init__.py
npb/management/commands/npb_generate_css.py
npb/management/commands/npb_purge_pastes.py
npb/migrations/0001_initial.py
npb/migrations/__init__.py
npb/static/npb/npb.css
npb/static/npb/pygments.css
npb/static/npb/reset.css
npb/templates/npb/base.html
npb/templates/npb/paste_detail.html
npb/templates/npb/paste_form.html
npb/templates/npb/report_form.html
npb/templatetags/__init__.py
npb/templatetags/recent_pastes.py
npb/tests/__init__.py
npb/tests/models.py
npb/tests/templatetags.py
django_npb-1.1.1.dist-info/LICENSE-EN.txt
django_npb-1.1.1.dist-info/LICENSE-FR.txt
django_npb-1.1.1.dist-info/METADATA
django_npb-1.1.1.dist-info/WHEEL
django_npb-1.1.1.dist-info/top_level.txt
django_npb-1.1.1.dist-info/RECORD
