Metadata-Version: 2.1
Name: django-npb
Version: 1.1.1
Summary: Pastebin module for Django
Home-page: https://github.com/breard-r/django-npb
Author: Rodolphe Bréard
Author-email: rodolphe@breard.tf
License: CeCILL-B
Keywords: django pastebin
Platform: UNKNOWN
Classifier: Development Status :: 5 - Production/Stable
Classifier: Framework :: Django
Classifier: Framework :: Django :: 2.2
Classifier: Framework :: Django :: 3.0
Classifier: License :: CeCILL-B Free Software License Agreement (CECILL-B)
Classifier: Programming Language :: Python :: 3.5
Classifier: Programming Language :: Python :: 3.6
Classifier: Programming Language :: Python :: 3.7
Classifier: Programming Language :: Python :: 3.8
Classifier: Programming Language :: Python :: 3 :: Only
Classifier: Programming Language :: Python :: Implementation :: CPython
Classifier: Programming Language :: Python :: Implementation :: PyPy
Classifier: Intended Audience :: Developers
Classifier: Topic :: Internet :: WWW/HTTP :: Dynamic Content
Requires-Python: ~=3.5
Requires-Dist: Django (<4.0,>=2.2)
Requires-Dist: Pygments (~=2.4)
Requires-Dist: pytimeparse (~=1.1)
